{
  "Prompts": [
    {
      "name": "publicPrompt",
      "method": "get",
      "path": "/prompts/:promptId",
      "type": "Query"
    },
    {
      "name": "publicPrompts",
      "method": "list",
      "path": "/prompts",
      "type": "Query"
    },
    {
      "name": "publicPromptRun",
      "method": "run",
      "path": "/prompts/run",
      "type": "Mutation"
    }
  ],
  "Targets": [
    {
      "name": "publicTargets",
      "method": "list",
      "path": "/targets",
      "type": "Query"
    },
    {
      "name": "publicTarget",
      "method": "get",
      "path": "/targets/:targetId",
      "type": "Query"
    }
  ],
  "Reactions": [
    {
      "name": "publicReactions",
      "method": "list",
      "path": "/reactions",
      "type": "Query"
    }
  ],
  "Metas": [
    {
      "name": "publicMeta",
      "method": "get",
      "path": "/metas/:metaId",
      "type": "Query"
    },
    {
      "name": "createMeta",
      "method": "create",
      "path": "metas/create",
      "type": "Mutation"
    },
    {
      "name": "publicMetas",
      "method": "list",
      "path": "/metas",
      "type": "Query"
    }
  ],
  "Logs": [
    {
      "name": "createLog",
      "method": "create",
      "path": "/logs/create",
      "type": "Mutation"
    }
  ],
  "Interests": [
    {
      "name": "createInterest",
      "method": "create",
      "path": "/interests/create",
      "type": "Mutation"
    }
  ],
  "Info": [
    {
      "name": "info",
      "method": "get",
      "path": "/info",
      "type": "Query"
    }
  ],
  "Files": [
    {
      "name": "upload",
      "method": "upload",
      "path": "/files/upload",
      "type": "Mutation"
    }
  ],
  "Contents": [
    {
      "name": "publicContent",
      "method": "get",
      "path": "/contents/:contentId",
      "type": "Query"
    },
    {
      "name": "publicContents",
      "method": "list",
      "path": "/contents",
      "type": "Query"
    }
  ],
  "Collections": [
    {
      "name": "publicCollection",
      "method": "get",
      "path": "/collections/:collectionId",
      "type": "Query"
    },
    {
      "name": "publicCollections",
      "method": "list",
      "path": "/collections",
      "type": "Query"
    }
  ],
  "Auth": [
    {
      "name": "registerTargets",
      "method": "registerTargets",
      "path": "/auth/register-targets",
      "type": "Mutation"
    },
    {
      "name": "isServiceConnected",
      "method": "isServiceConnected",
      "path": "/auth/is-service-connected",
      "type": "Query"
    },
    {
      "name": "loginWithToken",
      "method": "loginWithToken",
      "path": "/auth/login-with-token",
      "type": "Mutation"
    },
    {
      "name": "connectWithService",
      "method": "connectWithService",
      "path": "/auth/connect-with-service",
      "type": "Mutation"
    },
    {
      "name": "createAccount",
      "method": "createAccount",
      "path": "/auth/create-account",
      "type": "Mutation"
    }
  ],
  "Accounts": [
    {
      "endpoints": [
        {
          "method": "me",
          "endpoints": [
            {
              "name": "me",
              "method": "get",
              "path": "/accounts/me",
              "type": "Query",
              "endpoints": [
                {
                  "collection": [
                    {
                      "name": "collections",
                      "method": "list",
                      "path": "/accounts/me/collections",
                      "type": "Query"
                    },
                    {
                      "name": "collectionsCreate",
                      "method": "create",
                      "path": "/accounts/me/collections/create",
                      "type": "Mutation"
                    },
                    {
                      "name": "collectionsDelete",
                      "method": "delete",
                      "path": "/accounts/me/collections/delete",
                      "type": "Mutation"
                    },
                    {
                      "name": "collectionsUpdate",
                      "method": "update",
                      "path": "/accounts/me/collections/update",
                      "type": "Mutation"
                    },
                    {
                      "name": "collectionsRemoveContentFromCollection",
                      "method": "removeContentFromCollection",
                      "path": "/accounts/me/collections/remove-content-from-collection",
                      "type": "Mutation"
                    },
                    {
                      "name": "collectionsAddContentToCollection",
                      "method": "addContentToCollection",
                      "path": "/accounts/me/collections/add-content-to-collection",
                      "type": "Mutation"
                    }
                  ],
                  "content": [
                    {
                      "name": "contents",
                      "method": "list",
                      "path": "/accounts/me/contents",
                      "type": "Query"
                    },
                    {
                      "name": "contentsCreate",
                      "method": "create",
                      "path": "/accounts/me/contents/create",
                      "type": "Mutation"
                    },
                    {
                      "name": "contentsDelete",
                      "method": "delete",
                      "path": "/accounts/me/contents/delete",
                      "type": "Mutation"
                    },
                    {
                      "name": "contentsUpdate",
                      "method": "update",
                      "path": "/accounts/me/contents/update",
                      "type": "Mutation"
                    },
                    {
                      "name": "getContent",
                      "method": "get",
                      "path": "/accounts/me/contents/:contentId",
                      "type": "Query"
                    }
                  ],
                  "device": [
                    {
                      "name": "devices",
                      "method": "list",
                      "path": "/accounts/me/devices",
                      "type": "Query"
                    },
                    {
                      "name": "devicesSave",
                      "method": "save",
                      "path": "/accounts/me/devices/save",
                      "type": "Mutation"
                    },
                    {
                      "name": "devicesUpdate",
                      "method": "update",
                      "path": "/accounts/me/devices/update",
                      "type": "Mutation"
                    },
                    {
                      "name": "devicesDelete",
                      "method": "delete",
                      "path": "/accounts/me/devices/delete",
                      "type": "Mutation"
                    },
                    {
                      "name": "getDevices",
                      "method": "get",
                      "path": "/accounts/me/devices/:deviceId",
                      "type": "Query"
                    }
                  ],
                  "interest": [
                    {
                      "name": "interests",
                      "method": "list",
                      "path": "/accounts/me/interests",
                      "type": "Query"
                    },
                    {
                      "name": "getInterest",
                      "method": "get",
                      "path": "/accounts/me/interests/:interestId",
                      "type": "Query"
                    },
                    {
                      "name": "interestsCreate",
                      "method": "create",
                      "path": "/accounts/me/interests/create",
                      "type": "Mutation"
                    },
                    {
                      "name": "interestsDelete",
                      "method": "delete",
                      "path": "/accounts/me/interests/delete",
                      "type": "Mutation"
                    }
                  ],
                  "location": [
                    {
                      "name": "locations",
                      "method": "list",
                      "path": "/accounts/me/locations",
                      "type": "Query"
                    },
                    {
                      "name": "locationsRegister",
                      "method": "register",
                      "path": "/accounts/me/locations/register",
                      "type": "Mutation"
                    },
                    {
                      "name": "locationsDeleteAll",
                      "method": "deleteAll",
                      "path": "/accounts/me/locations/delete-all",
                      "type": "Mutation"
                    },
                    {
                      "name": "locationCreate",
                      "method": "create",
                      "path": "/accounts/me/locations/create",
                      "type": "Mutation"
                    }
                  ],
                  "log": [
                    {
                      "name": "logs",
                      "method": "list",
                      "path": "/accounts/me/logs",
                      "type": "Query"
                    }
                  ],
                  "prompt": [
                    {
                      "name": "prompts",
                      "method": "list",
                      "path": "/accounts/me/prompts",
                      "type": "Query"
                    },
                    {
                      "name": "getPrompt",
                      "method": "get",
                      "path": "/accounts/me/prompts/:promptId",
                      "type": "Query"
                    },
                    {
                      "name": "createPrompt",
                      "method": "create",
                      "path": "/accounts/me/prompts/create",
                      "type": "Mutation"
                    },
                    {
                      "name": "updatePrompt",
                      "method": "update",
                      "path": "/accounts/me/prompts/update",
                      "type": "Mutation"
                    },
                    {
                      "name": "deletePrompt",
                      "method": "delete",
                      "path": "/accounts/me/prompts/delete",
                      "type": "Mutation"
                    }
                  ],
            }
          ]
        }
      ]
    }
  ]
}
